cond_rnn/__init__.py
cond_rnn/cond_rnn.py
cond_rnn-3.2.2.dist-info/LICENSE
cond_rnn-3.2.2.dist-info/METADATA
cond_rnn-3.2.2.dist-info/WHEEL
cond_rnn-3.2.2.dist-info/top_level.txt
cond_rnn-3.2.2.dist-info/RECORD
