Metadata-Version: 2.1
Name: cond-rnn
Version: 3.2.2
Summary: Conditional RNN
Author: Philippe Remy
License: MIT
License-File: LICENSE
Requires-Dist: numpy
Requires-Dist: tensorflow
Requires-Dist: tensorflow-addons
Requires-Dist: protobuf (<=3.20)
